odoo10_addon_base_directory_file_download-10.0.1.0.0.99.dev6-py3.8-nspkg.pth
odoo/addons/base_directory_file_download/README.rst
odoo/addons/base_directory_file_download/__init__.py
odoo/addons/base_directory_file_download/__manifest__.py
odoo/addons/base_directory_file_download/i18n/base_directory_file_download.pot
odoo/addons/base_directory_file_download/models/__init__.py
odoo/addons/base_directory_file_download/models/ir_filesystem_directory.py
odoo/addons/base_directory_file_download/models/ir_filesystem_file.py
odoo/addons/base_directory_file_download/readme/CONFIGURE.rst
odoo/addons/base_directory_file_download/readme/CONTRIBUTORS.rst
odoo/addons/base_directory_file_download/readme/DESCRIPTION.rst
odoo/addons/base_directory_file_download/readme/USAGE.rst
odoo/addons/base_directory_file_download/security/groups.xml
odoo/addons/base_directory_file_download/security/ir.model.access.csv
odoo/addons/base_directory_file_download/static/description/icon.png
odoo/addons/base_directory_file_download/static/description/index.html
odoo/addons/base_directory_file_download/tests/__init__.py
odoo/addons/base_directory_file_download/tests/test_directory_files_download.py
odoo/addons/base_directory_file_download/views/ir_filesystem_directory.xml
odoo10_addon_base_directory_file_download-10.0.1.0.0.99.dev6.dist-info/METADATA
odoo10_addon_base_directory_file_download-10.0.1.0.0.99.dev6.dist-info/WHEEL
odoo10_addon_base_directory_file_download-10.0.1.0.0.99.dev6.dist-info/namespace_packages.txt
odoo10_addon_base_directory_file_download-10.0.1.0.0.99.dev6.dist-info/top_level.txt
odoo10_addon_base_directory_file_download-10.0.1.0.0.99.dev6.dist-info/RECORD
